[
{ "campo": "Alexandre e Bruna - Guilherme e Lais - Guilherme"},
{ "campo": "Alexandre e Bruna - Guilherme e Lais - Lucas"},
{ "campo": "Alexandre e Bruna - Guilherme e Lais - Thais"},
{ "campo": "Alexandre e Bruna - Johnny - Lenon e Islene"},
{ "campo": "Alexandre e Bruna - Johnny - Leticia"},
{ "campo": "Alexandre e Bruna - Johnny - Tiago"},
{ "campo": "Alexandre e Bruna - Marlon e Uyara - Erik e Luma"},
{ "campo": "Alexandre e Bruna - Marlon e Uyara - Mozart e Apoena"},
{ "campo": "Alexandre e Bruna - Marlon e Uyara - Philip e Katharine"},
{ "campo": "Alexandre e Bruna - Marlon e Uyara - Rafael e Janaina"},
{ "campo": "Alexandre e Bruna - Marlon e Uyara - Victor"},
{ "campo": "Alexandre e Bruna - Mateus - Caroline"},
{ "campo": "Alexandre e Bruna - Mateus - Mateus Mota"},
{ "campo": "Alexandre e Bruna - Vitor Aba - Diego"},
{ "campo": "Alexandre e Bruna - Vitor Aba - Fernando e Bruna"},
{ "campo": "Alexandre e Bruna - Vitor Aba - Giovanna Brunelli"},
{ "campo": "Alexandre e Bruna - Vitor Aba - Giovanna Conceição"},
{ "campo": "Alexandre e Bruna - Vitor Aba - Leonardo"},
{ "campo": "Alexandre e Bruna - Vitor Aba - Rebeca"},
{ "campo": "Alexandre e Bruna - Vitor e Pamela - Leticia"},
{ "campo": "Alexandre e Bruna - Vitor e Pamela - Nicole"},
{ "campo": "Alexandre e Bruna - Vitor e Pamela - Paloma"},
{ "campo": "Alisson e Camila - Alexandre - Fernando"},
{ "campo": "Alisson e Camila - Alexandre - Sabrina"},
{ "campo": "Alisson e Camila - Alexandre - Stefanie"},
{ "campo": "Alisson e Camila - Alexandre - Thais"},
{ "campo": "Alisson e Camila - Anderson e Gleicy - Anderson"},
{ "campo": "Alisson e Camila - Anderson e Gleicy - Fernando"},
{ "campo": "Alisson e Camila - Celso - Beatriz"},
{ "campo": "Alisson e Camila - Celso - Giovana"},
{ "campo": "Alisson e Camila - Celso - Kamila"},
{ "campo": "Alisson e Camila - Celso - Michele"},
{ "campo": "Alisson e Camila - Celso - Rodrigo"},
{ "campo": "Alisson e Camila - Genival e Marinete - Elton"},
{ "campo": "Alisson e Camila - Genival e Marinete - Francisca"},
{ "campo": "Alisson e Camila - Genival e Marinete - Thiago"},
{ "campo": "Alisson e Camila - Genival e Marinete - Vamires"},
{ "campo": "Alisson e Camila - Janielson - Elisa"},
{ "campo": "Alisson e Camila - Janielson - Jorge"},
{ "campo": "Alisson e Camila - Janielson - Vagner"},
{ "campo": "Alisson e Camila - Raphael e Daiane - Brendo"},
{ "campo": "Alisson e Camila - Raphael e Daiane - Fabio"},
{ "campo": "Alisson e Camila - Raphael e Daiane - Franciele"},
{ "campo": "Alisson e Camila - Raphael e Daiane - Igor e Maiara"},
{ "campo": "Alisson e Camila - Raphael e Daiane - Sandro e Risia"},
{ "campo": "Edson e Joice - Edson e Joice - Weverton"},
{ "campo": "Edson e Joice - Magson e Jessica - Glaucye"},
{ "campo": "Edson e Joice - Magson e Jessica - Joyce"},
{ "campo": "Edson e Joice - Magson e Jessica - Lucas"},
{ "campo": "Edson e Joice - Magson e Jessica - Magson e Jessica"},
{ "campo": "Edson e Joice - Magson e Jessica - Washington"},
{ "campo": "Edson e Joice - Mauricio e Vanessa - Douglas e Tati"},
{ "campo": "Edson e Joice - Mauricio e Vanessa - Edicarlos e Rose"},
{ "campo": "Edson e Joice - Mauricio e Vanessa - Hugo e Gabi"},
{ "campo": "Edson e Joice - Mauricio e Vanessa - Lucas e Leticia"},
{ "campo": "Edson e Joice - Mauricio e Vanessa - Mauricio e Vanessa"},
{ "campo": "Edson e Joice - Mauricio e Vanessa - Sergio e Aline"},
{ "campo": "Edson e Joice - Sol e Paula - Bruno e Raiane"},
{ "campo": "Edson e Joice - Sol e Paula - Jhonata"},
{ "campo": "Edson e Joice - Sol e Paula - Priscila"},
{ "campo": "Edson e Joice - Sol e Paula - Tacivan e Jessica"},
{ "campo": "Edson e Joice - Sol e Paula - Vitoria"},
{ "campo": "Eduardo e Simone - Eduardo e Simone - Andre"},
{ "campo": "Eduardo e Simone - Eduardo e Simone - Eribaldo e Neide"},
{ "campo": "Eduardo e Simone - Eduardo e Simone - Ivan e Fernanda"},
{ "campo": "Eduardo e Simone - Eduardo e Simone - Marcel e Isabela"},
{ "campo": "Eduardo e Simone - Eduardo e Simone - Rafaela"},
{ "campo": "Eduardo e Simone - Eduardo e Simone - Thayna"},
{ "campo": "Eduardo e Simone - Eduardo e Simone - Victor"},
{ "campo": "Eduardo e Simone - Erick e Monica - Eric e Tiffany"},
{ "campo": "Eduardo e Simone - Erick e Monica - Lucas"},
{ "campo": "Eduardo e Simone - Erick e Monica - Matheus e Juliana"},
{ "campo": "Eduardo e Simone - Erick e Monica - Vitor e Niccoly"},
{ "campo": "Eduardo e Simone - Rafael e Ivone - Cleyton e Karine"},
{ "campo": "Eduardo e Simone - Rafael e Ivone - Itamar e Quezia"},
{ "campo": "Eduardo e Simone - Rafael e Ivone - Johnny e Fernanda"},
{ "campo": "Eduardo e Simone - Rafael e Ivone - Maiara"},
{ "campo": "Eduardo e Simone - Viviane - Mayara"},
{ "campo": "Eduardo e Simone - Viviane - Stephany"},
{ "campo": "Eduardo e Simone - Viviane - Tifani de Souza"},
{ "campo": "Eduardo e Simone - Viviane - Vitoria"},
{ "campo": "Felipe e Luciana - Rafael e Fabiane - Ariana"},
{ "campo": "Felipe e Luciana - Rafael e Fabiane - Marcio e Ana"},
{ "campo": "Felipe e Luciana - Rafael e Fabiane - Rafael e Daiana"},
{ "campo": "Felipe e Luciana - Rafael e Fabiane - Ronaldo e Gyselle"},
{ "campo": "Felipe e Luciana - Rafael e Fabiane - Tiago e Bruna"},
{ "campo": "Felipe e Luciana - Ricardo e Ericka - Diego e Samara"},
{ "campo": "Felipe e Luciana - Ricardo e Ericka - Rafael e Laiza"},
{ "campo": "Felipe e Luciana - Ricardo e Ericka - Ricardo e Ericka"},
{ "campo": "Felipe e Luciana - Ricardo e Ericka - Vinicius e Liliane"},
{ "campo": "Felipe e Luciana - Robinson e Lidiane - Kevernilson"},
{ "campo": "Felipe e Luciana - Robinson e Lidiane - Mariana"},
{ "campo": "Felipe e Luciana - Robinson e Lidiane - Robinson"},
{ "campo": "Felipe e Luciana - Robinson e Natalia - Anderson e Joice"},
{ "campo": "Felipe e Luciana - Robinson e Natalia - Bruno e Ingrid"},
{ "campo": "Felipe e Luciana - Robinson e Natalia - Janaina"},
{ "campo": "Felipe e Luciana - Robinson e Natalia - Robinson e Natalia"},
{ "campo": "Fernando e Talita - Caroline - Moises"},
{ "campo": "Fernando e Talita - Caroline - Paulo Roberto"},
{ "campo": "Fernando e Talita - Caroline - Priscila"},
{ "campo": "Fernando e Talita - Caroline - Thalita"},
{ "campo": "Fernando e Talita - Fernando e Talita - André"},
{ "campo": "Fernando e Talita - Fernando e Talita - Bruna"},
{ "campo": "Fernando e Talita - Fernando e Talita - Emilly"},
{ "campo": "Fernando e Talita - Fernando e Talita - Maiara"},
{ "campo": "Fernando e Talita - Guilherme - Edvaldo"},
{ "campo": "Fernando e Talita - Guilherme - Gustavo"},
{ "campo": "Fernando e Talita - Guilherme - Leticia"},
{ "campo": "Fernando e Talita - Guilherme - Sabrina"},
{ "campo": "Fernando e Talita - Milena - Beatriz"},
{ "campo": "Fernando e Talita - Milena - Daniele"},
{ "campo": "Fernando e Talita - Milena - Giovana"},
{ "campo": "Fernando e Talita - Milena - Julia"},
{ "campo": "Fernando e Talita - Milena - Lais"},
{ "campo": "Fernando e Talita - Milena - Milena"},
{ "campo": "Fernando e Talita - Milena - Poliana"},
{ "campo": "Fernando e Talita - Richard - Eduardo"},
{ "campo": "Fernando e Talita - Richard - Emanuel"},
{ "campo": "Fernando e Talita - Richard - Higor"},
{ "campo": "Fernando e Talita - Richard - Leonardo"},
{ "campo": "Fernando e Talita - Richard - Lucas Dantas"},
{ "campo": "Fernando e Talita - Richard - Lucas Lopes"},
{ "campo": "Gleison e Vivian - Alecsandro e Marcia - João e Beatriz"},
{ "campo": "Gleison e Vivian - Alecsandro e Marcia - Marlon e Andressa"},
{ "campo": "Gleison e Vivian - Alecsandro e Marcia - Roberto"},
{ "campo": "Gleison e Vivian - Alecsandro e Marcia - Wesley e Bruna"},
{ "campo": "Gleison e Vivian - Leandro e Marcela - Fabio Rocha"},
{ "campo": "Gleison e Vivian - Leandro e Marcela - Leandro"},
{ "campo": "Gleison e Vivian - Leandro e Marcela - Rodrigo e Glecia"},
{ "campo": "Gleison e Vivian - Leandro e Marcela - Sabrina"},
{ "campo": "Gleison e Vivian - Márcio e Marina - Bruno e Helen"},
{ "campo": "Gleison e Vivian - Márcio e Marina - Leonardo e Ligia"},
{ "campo": "Gleison e Vivian - Márcio e Marina - Rafael e Juliana"},
{ "campo": "Gleison e Vivian - Márcio e Marina - Vini e Eli"},
{ "campo": "Gleison e Vivian - Marcio e Natali - Bady e Nati"},
{ "campo": "Gleison e Vivian - Marcio e Natali - Will e Amanda"},
{ "campo": "Gleison e Vivian - Marcos e Jessica - Marcos e Jessica"},
{ "campo": "Gleison e Vivian - Marcos e Jessica - Thayna"},
{ "campo": "Gleison e Vivian - Neto e Renata - Jean Claudio"},
{ "campo": "Gleison e Vivian - Neto e Renata - Jean David"},
{ "campo": "Gleison e Vivian - Neto e Renata - Luana"},
{ "campo": "Gleison e Vivian - Robson e Renata - Eduardo e Vanessa"},
{ "campo": "Gleison e Vivian - Robson e Renata - Fabio e Cris"},
{ "campo": "Gleison e Vivian - Robson e Renata - Robson e Renata"},
{ "campo": "Henrique e Camila - Henrique e Camila - Isabelle"},
{ "campo": "Henrique e Camila - Henrique e Camila - Lucas de Matos"},
{ "campo": "Henrique e Camila - Henrique e Camila - Nathalia"},
{ "campo": "Henrique e Camila - Henrique e Camila - Talita"},
{ "campo": "Henrique e Camila - Henrique e Camila - Thiago"},
{ "campo": "Henrique e Camila - Julio e Barbara - Amanda"},
{ "campo": "Henrique e Camila - Julio e Barbara - Diego"},
{ "campo": "Henrique e Camila - Julio e Barbara - Iverson"},
{ "campo": "Henrique e Camila - Julio e Barbara - Katia"},
{ "campo": "Henrique e Camila - Julio e Barbara - Marcus"},
{ "campo": "Henrique e Camila - Julio e Barbara - Vitor"},
{ "campo": "Henrique e Camila - Marconi e Heloisa - David e Priscila"},
{ "campo": "Henrique e Camila - Marconi e Heloisa - Giulia"},
{ "campo": "Henrique e Camila - Marconi e Heloisa - Helena"},
{ "campo": "Henrique e Camila - Marconi e Heloisa - Jessica"},
{ "campo": "Henrique e Camila - Marconi e Heloisa - Vitor"},
{ "campo": "Hugo e Barbara - Ana Paula - Fabricio"},
{ "campo": "Hugo e Barbara - Ana Paula - Felipe"},
{ "campo": "Hugo e Barbara - Ana Paula - Jennifer"},
{ "campo": "Hugo e Barbara - Ana Paula - Leticia"},
{ "campo": "Hugo e Barbara - Ana Paula - Pedro"},
{ "campo": "Hugo e Barbara - Hugo e Barbara - Amanda"},
{ "campo": "Hugo e Barbara - Hugo e Barbara - Ana Carolina"},
{ "campo": "Hugo e Barbara - Hugo e Barbara - Beatriz"},
{ "campo": "Hugo e Barbara - Hugo e Barbara - Cintia"},
{ "campo": "Hugo e Barbara - Hugo e Barbara - Diego"},
{ "campo": "Hugo e Barbara - Hugo e Barbara - Halana"},
{ "campo": "Hugo e Barbara - Hugo e Barbara - Hugo e Barbara"},
{ "campo": "Hugo e Barbara - Hugo e Barbara - Maria Isabel"},
{ "campo": "Hugo e Barbara - Hugo e Barbara - Mariana"},
{ "campo": "Hugo e Barbara - Hugo e Barbara - Nicolly"},
{ "campo": "Hugo e Barbara - Hugo e Barbara - Rayssa"},
{ "campo": "Hugo e Barbara - Hugo e Barbara - Stefany"},
{ "campo": "Hugo e Barbara - Hugo e Barbara - Vitor"},
{ "campo": "Hugo e Barbara - Lincoln e Catherine - Alexandre"},
{ "campo": "Hugo e Barbara - Lincoln e Catherine - Caroline"},
{ "campo": "Hugo e Barbara - Lincoln e Catherine - Gabrielle"},
{ "campo": "Hugo e Barbara - Lincoln e Catherine - Milena"},
{ "campo": "Hugo e Barbara - Lincoln e Catherine - Nathalia"},
{ "campo": "Hugo e Barbara - Lincoln e Catherine - Phelipe"},
{ "campo": "Hugo e Barbara - Lincoln e Catherine - Vitoria"},
{ "campo": "Leonardo - Filipe - Matheus Martins"},
{ "campo": "Leonardo - Filipe - Vitor Ribas"},
{ "campo": "Leonardo - Germano e Fernanda - Fernanda"},
{ "campo": "Leonardo - Germano e Fernanda - Germano"},
{ "campo": "Leonardo - Germano e Fernanda - Jose e Natali"},
{ "campo": "Leonardo - Germano e Fernanda - Vinicius"},
{ "campo": "Leonardo - Leonardo - Amanda"},
{ "campo": "Leonardo - Leonardo - Carlos Henrique"},
{ "campo": "Leonardo - Leonardo - Gabriel"},
{ "campo": "Leonardo - Leonardo - Guilherme Raina"},
{ "campo": "Leonardo - Leonardo - Vitor e Daiane"},
{ "campo": "Lirow Jhow - Filipe e Gabriela - Arianny"},
{ "campo": "Lirow Jhow - Filipe e Gabriela - Gabriel"},
{ "campo": "Lirow Jhow - Filipe e Gabriela - Rafael"},
{ "campo": "Lirow Jhow - Filipe e Gabriela - Sarah"},
{ "campo": "Lirow Jhow - Leticia - Felipe Garcia"},
{ "campo": "Lirow Jhow - Leticia - Giovana Katrine"},
{ "campo": "Lirow Jhow - Leticia - Marcela Pedro"},
{ "campo": "Lirow Jhow - Maressa - Aline"},
{ "campo": "Lirow Jhow - Maressa - Bruna"},
{ "campo": "Lirow Jhow - Maressa - Gabrielly"},
{ "campo": "Lirow Jhow - Maressa - Giovanna"},
{ "campo": "Lirow Jhow - Maressa - Maria Clara"},
{ "campo": "Lirow Jhow - Renan e Virginia - Clayton"},
{ "campo": "Lirow Jhow - Renan e Virginia - Leticia"},
{ "campo": "Lirow Jhow - Renan e Virginia - Pamela"},
{ "campo": "Lirow Jhow - Renan e Virginia - Raiane"},
{ "campo": "Lirow Jhow - Shell e Larissa - Bruno"},
{ "campo": "Lirow Jhow - Shell e Larissa - Ingrid"},
{ "campo": "Lirow Jhow - Shell e Larissa - Lucas"},
{ "campo": "Lirow Jhow - Shell e Larissa - Milton"},
{ "campo": "Lirow Jhow - Shell e Larissa - Natalia"},
{ "campo": "Lirow Jhow - Shell e Larissa - Rogerio e Beatriz"},
{ "campo": "Lirow Jhow - Shell e Larissa - Vanessa"},
{ "campo": "Lirow Jhow - Shell e Larissa - Victor"},
{ "campo": "Lirow Jhow - Shell e Larissa - Yasmin"},
{ "campo": "Manoel e Juliana - Adiel e Priscila - Admir"},
{ "campo": "Manoel e Juliana - Adiel e Priscila - Michel e Cleri"},
{ "campo": "Manoel e Juliana - Lais - Anna Karoline"},
{ "campo": "Manoel e Juliana - Lais - Guilherme"},
{ "campo": "Manoel e Juliana - Lais - Leandro"},
{ "campo": "Manoel e Juliana - Lais - Lucas"},
{ "campo": "Manoel e Juliana - Lais - Lucas"},
{ "campo": "Manoel e Juliana - Leonardo e Kacia - Ademir e Priscila"},
{ "campo": "Manoel e Juliana - Leonardo e Kacia - Edmarcio"},
{ "campo": "Manoel e Juliana - Leonardo e Kacia - Henrique e Keli"},
{ "campo": "Manoel e Juliana - Leonardo e Kacia - Lucas"},
{ "campo": "Manoel e Juliana - Leonardo e Kacia - Thalia"},
{ "campo": "Manoel e Juliana - Manoel e Juliana - Jesiel e Thaisa"},
{ "campo": "Manoel e Juliana - Matheus - Aline"},
{ "campo": "Manoel e Juliana - Matheus - Gregory"},
{ "campo": "Manoel e Juliana - Matheus - Matheus"},
{ "campo": "Manoel e Juliana - Matheus - Thina"},
{ "campo": "Manoel e Juliana - Paulo e Ligia - Barbara"},
{ "campo": "Manoel e Juliana - Paulo e Ligia - Flavio e Paola"},
{ "campo": "Manoel e Juliana - Paulo e Ligia - Paulo e Camila"},
{ "campo": "Manoel e Juliana - Paulo e Ligia - Walter e Edna"},
{ "campo": "Manoel e Juliana - Rafael e Shirlei - Amanda"},
{ "campo": "Manoel e Juliana - Rafael e Shirlei - Camila"},
{ "campo": "Manoel e Juliana - Rafael e Shirlei - Gabrielle"},
{ "campo": "Manoel e Juliana - Rafael e Shirlei - Leandro"},
{ "campo": "Manoel e Juliana - Rafael e Shirlei - Nathalie"},
{ "campo": "Manoel e Juliana - Rafael e Shirlei - Thiago e Isabella"},
{ "campo": "Manoel e Juliana - Renata - Evani"},
{ "campo": "Manoel e Juliana - Renata - Marcelo"},
{ "campo": "Manoel e Juliana - Renata - Marisa"},
{ "campo": "Manoel e Juliana - Renata - Sabrina"},
{ "campo": "Manoel e Juliana - Renata - Suelen"},
{ "campo": "Manoel e Juliana - Renata - Tatiane"},
{ "campo": "Manoel e Juliana - Renata - Yorrani"},
{ "campo": "Manoel e Juliana - Rogerio e Patricia - Diogo e Aylanna"},
{ "campo": "Manoel e Juliana - Rogerio e Patricia - Edileusa"},
{ "campo": "Manoel e Juliana - Rogerio e Patricia - Igor e Livia"},
{ "campo": "Manoel e Juliana - Thiago e Luisa - Danilo"},
{ "campo": "Manoel e Juliana - Thiago e Luisa - David e Tais"},
{ "campo": "Manoel e Juliana - Thiago e Luisa - Edison e Marta"},
{ "campo": "Manoel e Juliana - Thiago e Luisa - Mario"},
{ "campo": "Manoel e Juliana - Thiago e Luisa - Thiago e Luisa"},
{ "campo": "Manoel e Juliana - Thiago e Luisa - Yasmani"},
{ "campo": "Manoel e Juliana - Toni e Fernanda - Isael e Ellen"},
{ "campo": "Manoel e Juliana - Toni e Fernanda - Toni e Fernanda"},
{ "campo": "Moisés e Sônia - Evelyn - "},
{ "campo": "Osmar e Vanessa - Anderson e Luciana - Anderson e Luciana"},
{ "campo": "Osmar e Vanessa - Anderson e Luciana - Bianca"},
{ "campo": "Osmar e Vanessa - Anderson e Luciana - Caio e Flavia"},
{ "campo": "Osmar e Vanessa - Anderson e Luciana - Larissa"},
{ "campo": "Osmar e Vanessa - Anderson e Luciana - Priscila"},
{ "campo": "Osmar e Vanessa - Daniele - Daniel Pizani"},
{ "campo": "Osmar e Vanessa - Daniele - Evandro e Amanda"},
{ "campo": "Osmar e Vanessa - Daniele - Jefferson e Daniele"},
{ "campo": "Osmar e Vanessa - Diego e Pamella - Alexandre e Natalia"},
{ "campo": "Osmar e Vanessa - Diego e Pamella - Caroline"},
{ "campo": "Osmar e Vanessa - Diego e Pamella - Lazaro e Jessica"},
{ "campo": "Osmar e Vanessa - Diego e Pamella - Leonardo e Carol"},
{ "campo": "Osmar e Vanessa - Diego e Pamella - Michaela"},
{ "campo": "Osmar e Vanessa - Diego e Pamella - Rebeca"},
{ "campo": "Osmar e Vanessa - Gilberto e Jessica - Richard"},
{ "campo": "Osmar e Vanessa - Gilberto e Jessica - Simone"},
{ "campo": "Osmar e Vanessa - Gilberto e Jessica - William"},
{ "campo": "Osmar e Vanessa - Joyce - Luciana"},
{ "campo": "Osmar e Vanessa - Joyce - Thiago Etiene"},
{ "campo": "Osmar e Vanessa - Joyce - Thiago Timoteo"},
{ "campo": "Osmar e Vanessa - Leandro e Talita - Leandro e Jessica"},
{ "campo": "Osmar e Vanessa - Leandro e Talita - Thiago e Andressa"},
{ "campo": "Osmar e Vanessa - Rodrigo e Janaina - Claudia"},
{ "campo": "Osmar e Vanessa - Rodrigo e Janaina - Diogo e Rosimeire"},
{ "campo": "Osmar e Vanessa - Rodrigo e Janaina - Fabricio e Fernanda"},
{ "campo": "Osmar e Vanessa - Rodrigo e Janaina - Fernando e Liria"},
{ "campo": "Osmar e Vanessa - Rodrigo e Janaina - Lourdes"},
{ "campo": "Alisson e Camila - Abner - Abner"},
{ "campo": "Alisson e Camila - Abner - Luana"},
{ "campo": "Alisson e Camila - Abner - Lucas"},
{ "campo": "Rodrigo e Carol - Bruno e Isnaela - Akira e Lilian"},
{ "campo": "Rodrigo e Carol - Bruno e Isnaela - Alexandre e Talita"},
{ "campo": "Rodrigo e Carol - Bruno e Isnaela - Edna"},
{ "campo": "Rodrigo e Carol - Bruno e Isnaela - Fernanda"},
{ "campo": "Rodrigo e Carol - Bruno e Isnaela - Leandro e Shirley"},
{ "campo": "Rodrigo e Carol - Bruno e Isnaela - Patrícia"},
{ "campo": "Rodrigo e Carol - Camila - Daniel e Emilly"},
{ "campo": "Rodrigo e Carol - Camila - Jaqueline"},
{ "campo": "Rodrigo e Carol - Camila - Karla"},
{ "campo": "Rodrigo e Carol - Camila - Thayane"},
{ "campo": "Rodrigo e Carol - Danilo - Fabio"},
{ "campo": "Rodrigo e Carol - Danilo - Jocenita"},
{ "campo": "Rodrigo e Carol - Danilo - Kelly"},
{ "campo": "Rodrigo e Carol - Danilo - Waleska"},
{ "campo": "Rodrigo e Carol - Darlan e Mariana - Alexandre"},
{ "campo": "Rodrigo e Carol - Darlan e Mariana - Darlan e Mariana"},
{ "campo": "Rodrigo e Carol - Edvaldo e Gabrielle - Bruno Azevedo"},
{ "campo": "Rodrigo e Carol - Edvaldo e Gabrielle - Caio e Roberta"},
{ "campo": "Rodrigo e Carol - Edvaldo e Gabrielle - Guilherme + Giulia"},
{ "campo": "Rodrigo e Carol - Edvaldo e Gabrielle - Thiago e Bruna"},
{ "campo": "Rodrigo e Carol - Edvaldo e Gabrielle - Thiago e Larissa + Vinícius"},
{ "campo": "Rodrigo e Carol - Fabio e Gabriela - Fabio e Gabriela"},
{ "campo": "Rodrigo e Carol - Fabio e Gabriela - Marcos e Leticia"},
{ "campo": "Rodrigo e Carol - Michel e Vanessa - Eder"},
{ "campo": "Rodrigo e Carol - Michel e Vanessa - Eduardo e Fabiola"},
{ "campo": "Rodrigo e Carol - Michel e Vanessa - Jardyson e Rose"},
{ "campo": "Rodrigo e Carol - Michel e Vanessa - Ricardo e Michele"},
{ "campo": "Rodrigo e Carol - Paulo Henriuque - Daniel"},
{ "campo": "Rodrigo e Carol - Paulo Henriuque - Renan"},
{ "campo": "Rodrigo e Carol - Paulo Henriuque - Tiago"},
{ "campo": "Rodrigo e Carol - Paulo Henriuque - Wellington"},
{ "campo": "Rodrigo e Carol - Renato e Cristiane - Douglas e Ellen"},
{ "campo": "Rodrigo e Carol - Renato e Cristiane - Fernando e Karen"},
{ "campo": "Rodrigo e Carol - Renato e Cristiane - Pamela"},
{ "campo": "Rodrigo e Carol - Renato e Cristiane - Robson"},
{ "campo": "Rodrigo e Carol - Ricardo e Carla - Beatriz"},
{ "campo": "Rodrigo e Carol - Ricardo e Carla - Carlos"},
{ "campo": "Rodrigo e Carol - Ricardo e Carla - Diego"},
{ "campo": "Rodrigo e Carol - Ricardo e Carla - Diego e Juliana"},
{ "campo": "Rodrigo e Carol - Ricardo e Carla - Everton"},
{ "campo": "Rodrigo e Carol - Ricardo e Carla - Fernando"},
{ "campo": "Rodrigo e Carol - Ricardo e Carla - Lucas"},
{ "campo": "Romario e Priscila - Alex e Joyce - Fabricio"},
{ "campo": "Romario e Priscila - Alex e Joyce - Jonatas"},
{ "campo": "Romario e Priscila - Alex e Joyce - Laura"},
{ "campo": "Romario e Priscila - Alex e Joyce - Marcio"},
{ "campo": "Romario e Priscila - Alex e Joyce - Marcos"},
{ "campo": "Romario e Priscila - Caio e Carolina - Alexandre"},
{ "campo": "Romario e Priscila - Caio e Carolina - Denis"},
{ "campo": "Romario e Priscila - Caio e Carolina - Edmilson Junior"},
{ "campo": "Romario e Priscila - Caio e Carolina - Emilly"},
{ "campo": "Romario e Priscila - Caio e Carolina - Luiz Claudio"},
{ "campo": "Romario e Priscila - Caio e Carolina - Melissa"},
{ "campo": "Romario e Priscila - Caio e Carolina - Natalia"},
{ "campo": "Romario e Priscila - Caio e Carolina - Ruana"},
{ "campo": "Romario e Priscila - Caio e Carolina - Sergio e Tamires"},
{ "campo": "Romario e Priscila - Nathalia - Beatriz"},
{ "campo": "Romario e Priscila - Nathalia - Janaina"},
{ "campo": "Romario e Priscila - Nathalia - Juliah"},
{ "campo": "Romario e Priscila - Nathalia - Nathalia"},
{ "campo": "Romario e Priscila - Nathalia - Thaisa"},
{ "campo": "Samuel e Ariadne - Diego e Thayna - Allison"},
{ "campo": "Samuel e Ariadne - Diego e Thayna - Cesar"},
{ "campo": "Samuel e Ariadne - Diego e Thayna - Damaris"},
{ "campo": "Samuel e Ariadne - Diego e Thayna - Izaias"},
{ "campo": "Samuel e Ariadne - Diego e Thayna - Leandro"},
{ "campo": "Samuel e Ariadne - Diego e Thayna - Maria Carolina"},
{ "campo": "Samuel e Ariadne - Diego e Thayna - Roger e Carol"},
{ "campo": "Samuel e Ariadne - Lucas Bispo - Caio"},
{ "campo": "Samuel e Ariadne - Lucas Bispo - Leandro e Maria"},
{ "campo": "Samuel e Ariadne - Lucas Bispo - Marcos "},
{ "campo": "Samuel e Ariadne - Lucas Bispo - Rafael e Barbi"},
{ "campo": "Samuel e Ariadne - Samuel e Vanessa - Alice"},
{ "campo": "Samuel e Ariadne - Samuel e Vanessa - Lucas"},
{ "campo": "Samuel e Ariadne - Samuel e Vanessa - Nara"},
{ "campo": "Samuel e Ariadne - Samuel e Vanessa - Samuel e Vanessa"},
{ "campo": "Samuel e Ariadne - Samuel e Vanessa - Thiago e Fernanda"},
{ "campo": "Samuel e Ariadne - Samuel e Vanessa - Vini e Ana"},
{ "campo": "Samuel e Ariadne - Willian e Carolina - Felipe"},
{ "campo": "Samuel e Ariadne - Willian e Carolina - Willian e Carolina"},
{ "campo": "Wash e Carla - Ariane - Andreia Lima"},
{ "campo": "Wash e Carla - Ariane - Andreia Ribeiro"},
{ "campo": "Wash e Carla - Ariane - Ariane"},
{ "campo": "Wash e Carla - Ariane - Maete"},
{ "campo": "Wash e Carla - Cleomar e Valeria - Daniel e Monica"},
{ "campo": "Wash e Carla - Cleomar e Valeria - Lucio"},
{ "campo": "Wash e Carla - Elisangela - Alice"},
{ "campo": "Wash e Carla - Elisangela - Cristiane"},
{ "campo": "Wash e Carla - Elisangela - Mateus"},
{ "campo": "Wash e Carla - Elisangela - Mikaela"},
{ "campo": "Wash e Carla - Elisangela - Samanta"},
{ "campo": "Wash e Carla - Elisangela - Sarah"},
{ "campo": "Wash e Carla - Gloria - Adriana"},
{ "campo": "Wash e Carla - Gloria - Gabrielle"},
{ "campo": "Wash e Carla - Gloria - Graciela"},
{ "campo": "Wash e Carla - Lei e Renata - Danilo Alves"},
{ "campo": "Wash e Carla - Lei e Renata - Danilo Souza"},
{ "campo": "Wash e Carla - Lei e Renata - Tiago"},
{ "campo": "Wash e Carla - Leonardo e Daniela - Adilson e Mariana"},
{ "campo": "Wash e Carla - Leonardo e Daniela - Bianca"},
{ "campo": "Wash e Carla - Leonardo e Daniela - Cesar e Tati"},
{ "campo": "Wash e Carla - Renato e Andreia - Carol"},
{ "campo": "Wash e Carla - Renato e Andreia - Daniel"},
{ "campo": "Wash e Carla - Renato e Andreia - Isabella"},
{ "campo": "Wash e Carla - Renato e Andreia - Isac"},
{ "campo": "Wash e Carla - Renato e Andreia - Luan"},
{ "campo": "Wash e Carla - Renato e Andreia - Sophia"}
]